opentab/__init__.py
opentab/opentab.py
opentab/command/__init__.py
opentab/command/add.py
opentab/command/list.py
opentab/command/open.py
opentab/command/remove.py
opentab/command/start.py
opentab/exception/GroupExists.py
opentab/exception/__init__.py
opentab/parsing/__init__.py
opentab/parsing/parse_cli_args.py
opentab/utility/__init__.py
opentab/utility/constants.py
opentab/utility/get_group_urls.py
opentab/utility/get_right_urls.py
opentab/utility/is_url_correct.py
opentab/yaml/__init__.py
opentab/yaml/read_yaml.py
opentab/yaml/write_yaml.py
opentab-0.0.6.dist-info/LICENSE
opentab-0.0.6.dist-info/METADATA
opentab-0.0.6.dist-info/WHEEL
opentab-0.0.6.dist-info/entry_points.txt
opentab-0.0.6.dist-info/top_level.txt
opentab-0.0.6.dist-info/RECORD
