Metadata-Version: 2.1
Name: opentab
Version: 0.0.6
Summary: Opentab groups browser tabs and let you open it whenever needed
Home-page: https://github.com/endriu00/opentab
Author: Opentab team
Author-email: 
License: UNKNOWN
Platform: UNKNOWN
Classifier: Programming Language :: Python :: 3
Classifier: License :: OSI Approved :: BSD License
Classifier: Operating System :: OS Independent
Requires-Python: >=3.6
License-File: LICENSE
Requires-Dist: colorama
Requires-Dist: ruamel.yaml
Requires-Dist: argparse
